Metadata-Version: 2.1
Name: defichain
Version: 3.1.3
Summary: Defichain Python Library
Home-page: https://github.com/eric-volz/DefichainPython
Author: Intr0c
Author-email: introc@volz.link
Keywords: python,defichain,node,ocean,mnemonic,wallet,privateKey,transactions,raw transactions,P2PKH,P2SH,P2WPKH,DefiTx,custom transaction
Classifier: Programming Language :: Python :: 3.7
Classifier: Programming Language :: Python :: 3.8
Classifier: Programming Language :: Python :: 3.9
Classifier: Programming Language :: Python :: 3.10
Classifier: Operating System :: Unix
Classifier: Operating System :: MacOS :: MacOS X
Classifier: Operating System :: Microsoft :: Windows
License-File: LICENSE
Requires-Dist: requests >=2.31.0
Requires-Dist: six >=1.16.0
Requires-Dist: ecdsa >=0.18.0
Requires-Dist: base58 >=2.1.1
Requires-Dist: pycryptodome >=3.18.0
